cryptic/__init__.py
microservicecryp-1.3.3.dist-info/METADATA
microservicecryp-1.3.3.dist-info/WHEEL
microservicecryp-1.3.3.dist-info/top_level.txt
microservicecryp-1.3.3.dist-info/RECORD
