Metadata-Version: 2.1
Name: microservicecryp
Version: 1.3.3
Summary: Microservice handler for cryptic-game
Home-page: https://github.com/cryptic-game/python3-lib
Author: cryptic-game
Author-email: faq@cryptic-game.net
License: UNKNOWN
Platform: UNKNOWN
